{
	"configurations" : 
	[
		{
			"directories" : 
			[
				{
					"build" : ".",
					"jsonFile" : "directory-.-Debug-f5ebdc15457944623624.json",
					"minimumCMakeVersion" : 
					{
						"string" : "3.21"
					},
					"projectIndex" : 0,
					"source" : ".",
					"targetIndexes" : 
					[
						0
					]
				}
			],
			"name" : "Debug",
			"projects" : 
			[
				{
					"directoryIndexes" : 
					[
						0
					],
					"name" : "friend_sample",
					"targetIndexes" : 
					[
						0
					]
				}
			],
			"targets" : 
			[
				{
					"directoryIndex" : 0,
					"id" : "friend_sample::@6890427a1f51a3e7e1df",
					"jsonFile" : "target-friend_sample-Debug-79d2e9c4c26c330bfbab.json",
					"name" : "friend_sample",
					"projectIndex" : 0
				}
			]
		}
	],
	"kind" : "codemodel",
	"paths" : 
	{
		"build" : "/Users/setsunayang/Documents/learning/learning/ccpp/friend_sample/cmake-build-debug",
		"source" : "/Users/setsunayang/Documents/learning/learning/ccpp/friend_sample"
	},
	"version" : 
	{
		"major" : 2,
		"minor" : 3
	}
}
